Models/Multistep_Models.py
Models/Multivariate_Input_Models.py
Models/Multivariate_Input_Multistep_Models.py
Models/Multivariate_Parallel_Models.py
Models/Multivariate_Parallel_Multistep_Models.py
Models/Univariate_Models.py
Models/__init__.py
Models/data_prep.py
Models/timeseries_to_supervised.py
Pow_Usage/CNN_LSTM_Encoder_Decoder_Model.py
Pow_Usage/ConvLSTM_Encoder_Decoder_Model.py
Pow_Usage/Eval_Summarize.py
Pow_Usage/LSTM_power_Model.py
Pow_Usage/Multivariate_Encoder_Decoder_Model.py
Pow_Usage/Univariate_Encoder_Decoder_Model.py
Pow_Usage/__init__.py
ForcastingModels-0.0.1.dist-info/LICENSE
ForcastingModels-0.0.1.dist-info/METADATA
ForcastingModels-0.0.1.dist-info/WHEEL
ForcastingModels-0.0.1.dist-info/top_level.txt
ForcastingModels-0.0.1.dist-info/RECORD
